<?xml version="1.0" encoding="UTF-8"?>
<addressBook>
	<adress>
		<Geschlecht>255</Geschlecht>
		<Name>Bellmann</Name>
		<Vorname>Kathrin</Vorname>
		<APID>33633</APID>
	</adress>
	<adress>
		<Geschlecht>255</Geschlecht>
		<Name>Kakutnum</Name>
		<Vorname>Sieger</Vorname>
		<APID>12</APID>
	</adress>
	<adress>
		<Geschlecht>0</Geschlecht>
		<Name>Vogel</Name>
		<Vorname>Blut</Vorname>
		<APID>33761</APID>
	</adress>
	<adress>
		<Geschlecht>0</Geschlecht>
		<Name>Vogel</Name>
		<Vorname>Blut</Vorname>
		<APID>33678</APID>
	</adress>
	<adress>
		<Geschlecht>0</Geschlecht>
		<Name>Regen</Name>
		<Vorname>Nase</Vorname>
		<APID>33679</APID>
	</adress>
	<adress>
		<Geschlecht>0</Geschlecht>
		<Name>Regen</Name>
		<Vorname>Nase</Vorname>
		<APID>33762</APID>
	</adress>
	<adress>
		<Geschlecht>0</Geschlecht>
		<Name>Hakan</Name>
		<Vorname>AlRein</Vorname>
		<APID>33763</APID>
	</adress>
	<adress>
		<Geschlecht>0</Geschlecht>
		<Name>Butterfinger</Name>
		<Vorname>John</Vorname>
		<APID>33764</APID>
	</adress>
	<adress>
		<Geschlecht>0</Geschlecht>
		<Name>Cuver</Name>
		<Vorname>Franziska</Vorname>
		<APID>33765</APID>
	</adress>
	<adress>
		<Geschlecht>0</Geschlecht>
		<Name>Bellmann</Name>
		<Vorname>asdsad</Vorname>
		<APID>33766</APID>
	</adress>
</addressBook>